<!DOCTYPE refSeg SYSTEM "shotBoundaryReferenceSegmentation.dtd">
<refSeg src="nad28.mpg" creationMethod="MANUAL" totalFNum="52927">
<trans type="CUT" preFNum="286" postFNum="287"/>
<trans type="CUT" preFNum="369" postFNum="370"/>
<trans type="CUT" preFNum="409" postFNum="410"/>
<trans type="CUT" preFNum="494" postFNum="495"/>
<trans type="CUT" preFNum="579" postFNum="580"/>
<trans type="CUT" preFNum="626" postFNum="627"/>
<trans type="CUT" preFNum="662" postFNum="663"/>
<trans type="CUT" preFNum="778" postFNum="779"/>
<trans type="CUT" preFNum="919" postFNum="920"/>
<trans type="FOI" preFNum="1011" postFNum="1070"/>
<trans type="FOI" preFNum="1343" postFNum="1383"/>
<trans type="DIS" preFNum="1634" postFNum="1672"/>
<trans type="DIS" preFNum="1677" postFNum="1720"/>
<trans type="DIS" preFNum="1725" postFNum="1822"/>
<trans type="DIS" preFNum="1842" postFNum="1919"/>
<trans type="FOI" preFNum="1980" postFNum="2054"/>
<trans type="DIS" preFNum="2163" postFNum="2185"/>
<trans type="DIS" preFNum="2368" postFNum="2405"/>
<trans type="DIS" preFNum="2426" postFNum="2453"/>
<trans type="DIS" preFNum="2465" postFNum="2486"/>
<trans type="DIS" preFNum="2496" postFNum="2518"/>
<trans type="DIS" preFNum="2561" postFNum="2584"/>
<trans type="DIS" preFNum="2651" postFNum="2664"/>
<trans type="DIS" preFNum="2729" postFNum="2738"/>
<trans type="DIS" preFNum="2919" postFNum="2929"/>
<trans type="DIS" preFNum="3246" postFNum="3262"/>
<trans type="CUT" preFNum="3351" postFNum="3352"/>
<trans type="DIS" preFNum="3527" postFNum="3543"/>
<trans type="CUT" preFNum="3689" postFNum="3690"/>
<trans type="DIS" preFNum="3852" postFNum="3880"/>
<trans type="DIS" preFNum="4127" postFNum="4146"/>
<trans type="DIS" preFNum="4424" postFNum="4441"/>
<trans type="CUT" preFNum="4494" postFNum="4495"/>
<trans type="CUT" preFNum="4585" postFNum="4586"/>
<trans type="CUT" preFNum="4862" postFNum="4863"/>
<trans type="DIS" preFNum="5290" postFNum="5302"/>
<trans type="DIS" preFNum="5807" postFNum="5819"/>
<trans type="DIS" preFNum="6025" postFNum="6040"/>
<trans type="CUT" preFNum="6316" postFNum="6317"/>
<trans type="CUT" preFNum="6832" postFNum="6833"/>
<trans type="CUT" preFNum="6908" postFNum="6909"/>
<trans type="CUT" preFNum="7033" postFNum="7034"/>
<trans type="CUT" preFNum="7105" postFNum="7106"/>
<trans type="CUT" preFNum="7162" postFNum="7163"/>
<trans type="CUT" preFNum="7337" postFNum="7338"/>
<trans type="CUT" preFNum="7500" postFNum="7501"/>
<trans type="CUT" preFNum="7755" postFNum="7756"/>
<trans type="CUT" preFNum="8004" postFNum="8005"/>
<trans type="CUT" preFNum="8163" postFNum="8164"/>
<trans type="CUT" preFNum="8279" postFNum="8280"/>
<trans type="DIS" preFNum="8425" postFNum="8436"/>
<trans type="DIS" preFNum="8489" postFNum="8493"/>
<trans type="DIS" preFNum="8540" postFNum="8544"/>
<trans type="DIS" preFNum="8579" postFNum="8591"/>
<trans type="CUT" preFNum="8706" postFNum="8707"/>
<trans type="DIS" preFNum="8926" postFNum="8939"/>
<trans type="CUT" preFNum="9021" postFNum="9022"/>
<trans type="DIS" preFNum="9043" postFNum="9067"/>
<trans type="DIS" preFNum="9159" postFNum="9181"/>
<trans type="DIS" preFNum="9271" postFNum="9300"/>
<trans type="DIS" preFNum="9330" postFNum="9343"/>
<trans type="DIS" preFNum="9380" postFNum="9389"/>
<trans type="DIS" preFNum="9519" postFNum="9526"/>
<trans type="DIS" preFNum="10083" postFNum="10095"/>
<trans type="DIS" preFNum="10428" postFNum="10455"/>
<trans type="DIS" preFNum="10663" postFNum="10681"/>
<trans type="DIS" preFNum="10885" postFNum="10900"/>
<trans type="DIS" preFNum="11728" postFNum="11739"/>
<trans type="DIS" preFNum="11792" postFNum="11820"/>
<trans type="CUT" preFNum="12057" postFNum="12058"/>
<trans type="CUT" preFNum="12224" postFNum="12225"/>
<trans type="DIS" preFNum="12552" postFNum="12571"/>
<trans type="DIS" preFNum="12849" postFNum="12875"/>
<trans type="DIS" preFNum="13124" postFNum="13146"/>
<trans type="DIS" preFNum="13301" postFNum="13315"/>
<trans type="DIS" preFNum="13459" postFNum="13471"/>
<trans type="DIS" preFNum="13566" postFNum="13591"/>
<trans type="DIS" preFNum="13804" postFNum="13835"/>
<trans type="DIS" preFNum="13948" postFNum="13967"/>
<trans type="CUT" preFNum="14069" postFNum="14070"/>
<trans type="CUT" preFNum="14133" postFNum="14134"/>
<trans type="CUT" preFNum="14161" postFNum="14162"/>
<trans type="CUT" preFNum="14219" postFNum="14220"/>
<trans type="CUT" preFNum="14292" postFNum="14293"/>
<trans type="CUT" preFNum="14407" postFNum="14408"/>
<trans type="CUT" preFNum="14565" postFNum="14566"/>
<trans type="CUT" preFNum="14620" postFNum="14621"/>
<trans type="CUT" preFNum="14680" postFNum="14681"/>
<trans type="DIS" preFNum="14981" postFNum="14993"/>
<trans type="CUT" preFNum="15124" postFNum="15125"/>
<trans type="CUT" preFNum="15215" postFNum="15216"/>
<trans type="DIS" preFNum="15374" postFNum="15385"/>
<trans type="CUT" preFNum="15609" postFNum="15610"/>
<trans type="DIS" preFNum="15660" postFNum="15671"/>
<trans type="DIS" preFNum="15764" postFNum="15773"/>
<trans type="DIS" preFNum="15848" postFNum="15862"/>
<trans type="CUT" preFNum="16024" postFNum="16036"/>
<trans type="DIS" preFNum="16398" postFNum="16411"/>
<trans type="DIS" preFNum="16604" postFNum="16616"/>
<trans type="DIS" preFNum="16790" postFNum="16802"/>
<trans type="DIS" preFNum="16963" postFNum="16980"/>
<trans type="CUT" preFNum="17439" postFNum="17440"/>
<trans type="CUT" preFNum="17526" postFNum="17527"/>
<trans type="CUT" preFNum="17552" postFNum="17553"/>
<trans type="CUT" preFNum="17599" postFNum="17600"/>
<trans type="CUT" preFNum="17820" postFNum="17821"/>
<trans type="CUT" preFNum="17939" postFNum="17940"/>
<trans type="CUT" preFNum="18000" postFNum="18001"/>
<trans type="CUT" preFNum="18083" postFNum="18084"/>
<trans type="CUT" preFNum="18368" postFNum="18369"/>
<trans type="DIS" preFNum="19103" postFNum="19120"/>
<trans type="DIS" preFNum="19407" postFNum="19451"/>
<trans type="DIS" preFNum="19648" postFNum="19667"/>
<trans type="DIS" preFNum="19769" postFNum="19794"/>
<trans type="CUT" preFNum="19871" postFNum="19872"/>
<trans type="CUT" preFNum="19992" postFNum="19993"/>
<trans type="CUT" preFNum="20083" postFNum="20084"/>
<trans type="CUT" preFNum="20216" postFNum="20217"/>
<trans type="CUT" preFNum="20390" postFNum="20391"/>
<trans type="CUT" preFNum="20527" postFNum="20528"/>
<trans type="CUT" preFNum="20624" postFNum="20625"/>
<trans type="CUT" preFNum="20731" postFNum="20732"/>
<trans type="CUT" preFNum="20810" postFNum="20811"/>
<trans type="CUT" preFNum="21039" postFNum="21040"/>
<trans type="CUT" preFNum="21131" postFNum="21132"/>
<trans type="CUT" preFNum="21269" postFNum="21270"/>
<trans type="CUT" preFNum="21308" postFNum="21309"/>
<trans type="CUT" preFNum="21471" postFNum="21472"/>
<trans type="DIS" preFNum="21686" postFNum="21698"/>
<trans type="CUT" preFNum="21941" postFNum="21942"/>
<trans type="CUT" preFNum="23058" postFNum="23059"/>
<trans type="CUT" preFNum="23450" postFNum="23451"/>
<trans type="CUT" preFNum="23653" postFNum="23654"/>
<trans type="CUT" preFNum="23778" postFNum="23779"/>
<trans type="CUT" preFNum="23929" postFNum="23920"/>
<trans type="CUT" preFNum="24011" postFNum="24012"/>
<trans type="CUT" preFNum="24072" postFNum="24073"/>
<trans type="CUT" preFNum="24548" postFNum="24549"/>
<trans type="CUT" preFNum="24838" postFNum="24839"/>
<trans type="CUT" preFNum="25146" postFNum="25147"/>
<trans type="CUT" preFNum="25442" postFNum="25443"/>
<trans type="CUT" preFNum="25684" postFNum="25685"/>
<trans type="CUT" preFNum="26030" postFNum="26031"/>
<trans type="CUT" preFNum="26174" postFNum="26175"/>
<trans type="DIS" preFNum="26332" postFNum="26351"/>
<trans type="FOI" preFNum="26550" postFNum="26607"/>
<trans type="CUT" preFNum="26867" postFNum="26868"/>
<trans type="CUT" preFNum="26938" postFNum="26939"/>
<trans type="DIS" preFNum="27059" postFNum="27072"/>
<trans type="CUT" preFNum="27193" postFNum="27194"/>
<trans type="CUT" preFNum="27275" postFNum="27276"/>
<trans type="CUT" preFNum="27441" postFNum="27442"/>
<trans type="DIS" preFNum="27529" postFNum="27541"/>
<trans type="FOI" preFNum="27598" postFNum="27713"/>
<trans type="CUT" preFNum="27800" postFNum="27801"/>
<trans type="DIS" preFNum="28056" postFNum="28068"/>
<trans type="DIS" preFNum="28338" postFNum="28347"/>
<trans type="DIS" preFNum="28585" postFNum="28597"/>
<trans type="CUT" preFNum="28852" postFNum="28853"/>
<trans type="DIS" preFNum="29075" postFNum="29092"/>
<trans type="DIS" preFNum="29442" postFNum="29461"/>
<trans type="FOI" preFNum="29547" postFNum="29590"/>
<trans type="CUT" preFNum="29783" postFNum="29784"/>
<trans type="DIS" preFNum="29944" postFNum="29957"/>
<trans type="CUT" preFNum="30132" postFNum="30133"/>
<trans type="DIS" preFNum="30296" postFNum="30306"/>
<trans type="DIS" preFNum="30639" postFNum="30649"/>
<trans type="CUT" preFNum="30739" postFNum="30740"/>
<trans type="CUT" preFNum="30865" postFNum="30866"/>
<trans type="CUT" preFNum="30945" postFNum="30946"/>
<trans type="CUT" preFNum="31141" postFNum="31142"/>
<trans type="CUT" preFNum="31290" postFNum="31291"/>
<trans type="CUT" preFNum="31454" postFNum="31455"/>
<trans type="CUT" preFNum="31740" postFNum="31741"/>
<trans type="CUT" preFNum="31895" postFNum="31896"/>
<trans type="CUT" preFNum="32065" postFNum="32066"/>
<trans type="CUT" preFNum="32312" postFNum="32313"/>
<trans type="CUT" preFNum="32458" postFNum="32459"/>
<trans type="CUT" preFNum="32510" postFNum="32511"/>
<trans type="CUT" preFNum="32598" postFNum="32599"/>
<trans type="CUT" preFNum="32741" postFNum="32742"/>
<trans type="CUT" preFNum="32820" postFNum="32821"/>
<trans type="CUT" preFNum="32928" postFNum="32929"/>
<trans type="DIS" preFNum="33008" postFNum="33020"/>
<trans type="CUT" preFNum="33332" postFNum="33333"/>
<trans type="CUT" preFNum="33483" postFNum="33484"/>
<trans type="CUT" preFNum="33550" postFNum="33551"/>
<trans type="CUT" preFNum="33691" postFNum="33692"/>
<trans type="CUT" preFNum="33735" postFNum="33736"/>
<trans type="CUT" preFNum="33797" postFNum="33798"/>
<trans type="CUT" preFNum="34087" postFNum="34088"/>
<trans type="CUT" preFNum="34301" postFNum="34302"/>
<trans type="CUT" preFNum="34388" postFNum="34389"/>
<trans type="CUT" preFNum="34702" postFNum="34703"/>
<trans type="CUT" preFNum="35145" postFNum="35146"/>
<trans type="CUT" preFNum="35235" postFNum="35236"/>
<trans type="CUT" preFNum="35428" postFNum="35429"/>
<trans type="CUT" preFNum="35655" postFNum="35656"/>
<trans type="CUT" preFNum="35863" postFNum="35864"/>
<trans type="CUT" preFNum="36096" postFNum="36097"/>
<trans type="DIS" preFNum="36300" postFNum="36315"/>
<trans type="DIS" preFNum="36541" postFNum="36571"/>
<trans type="FOI" preFNum="36806" postFNum="36836"/>
<trans type="CUT" preFNum="37175" postFNum="37176"/>
<trans type="DIS" preFNum="37277" postFNum="37292"/>
<trans type="CUT" preFNum="37373" postFNum="37374"/>
<trans type="CUT" preFNum="37509" postFNum="37510"/>
<trans type="FOI" preFNum="37663" postFNum="37707"/>
<trans type="DIS" preFNum="37841" postFNum="37859"/>
<trans type="CUT" preFNum="38164" postFNum="38165"/>
<trans type="CUT" preFNum="38243" postFNum="38244"/>
<trans type="CUT" preFNum="38478" postFNum="38479"/>
<trans type="DIS" preFNum="38752" postFNum="38763"/>
<trans type="CUT" preFNum="38983" postFNum="38984"/>
<trans type="CUT" preFNum="39106" postFNum="39107"/>
<trans type="DIS" preFNum="39218" postFNum="39231"/>
<trans type="DIS" preFNum="39357" postFNum="39365"/>
<trans type="CUT" preFNum="39448" postFNum="39449"/>
<trans type="DIS" preFNum="39549" postFNum="39560"/>
<trans type="DIS" preFNum="40094" postFNum="40105"/>
<trans type="DIS" preFNum="40348" postFNum="40368"/>
<trans type="DIS" preFNum="40467" postFNum="40483"/>
<trans type="CUT" preFNum="40713" postFNum="40714"/>
<trans type="CUT" preFNum="40932" postFNum="40933"/>
<trans type="DIS" preFNum="41160" postFNum="41182"/>
<trans type="CUT" preFNum="41272" postFNum="41273"/>
<trans type="CUT" preFNum="41446" postFNum="41447"/>
<trans type="DIS" preFNum="41537" postFNum="41549"/>
<trans type="CUT" preFNum="41672" postFNum="41673"/>
<trans type="CUT" preFNum="41722" postFNum="41723"/>
<trans type="CUT" preFNum="41777" postFNum="41778"/>
<trans type="DIS" preFNum="41854" postFNum="41866"/>
<trans type="CUT" preFNum="42038" postFNum="42039"/>
<trans type="DIS" preFNum="42247" postFNum="42267"/>
<trans type="CUT" preFNum="42302" postFNum="42303"/>
<trans type="DIS" preFNum="42401" postFNum="42440"/>
<trans type="FOI" preFNum="42787" postFNum="42845"/>
<trans type="DIS" preFNum="43015" postFNum="43034"/>
<trans type="DIS" preFNum="43115" postFNum="43135"/>
<trans type="DIS" preFNum="43208" postFNum="43220"/>
<trans type="DIS" preFNum="43271" postFNum="43283"/>
<trans type="DIS" preFNum="43365" postFNum="43384"/>
<trans type="DIS" preFNum="43595" postFNum="43618"/>
<trans type="DIS" preFNum="43668" postFNum="43715"/>
<trans type="DIS" preFNum="43766" postFNum="43783"/>
<trans type="CUT" preFNum="43965" postFNum="43966"/>
<trans type="DIS" preFNum="44115" postFNum="44135"/>
<trans type="DIS" preFNum="44317" postFNum="44365"/>
<trans type="CUT" preFNum="44549" postFNum="44550"/>
<trans type="CUT" preFNum="44590" postFNum="44591"/>
<trans type="CUT" preFNum="44663" postFNum="44664"/>
<trans type="CUT" preFNum="44753" postFNum="44754"/>
<trans type="CUT" preFNum="44924" postFNum="44925"/>
<trans type="DIS" preFNum="45074" postFNum="45081"/>
<trans type="DIS" preFNum="45250" postFNum="45263"/>
<trans type="CUT" preFNum="45483" postFNum="45484"/>
<trans type="CUT" preFNum="45531" postFNum="45532"/>
<trans type="CUT" preFNum="45607" postFNum="45608"/>
<trans type="CUT" preFNum="45779" postFNum="45780"/>
<trans type="CUT" preFNum="45867" postFNum="45868"/>
<trans type="CUT" preFNum="45957" postFNum="45948"/>
<trans type="CUT" preFNum="46039" postFNum="46040"/>
<trans type="DIS" preFNum="46226" postFNum="46260"/>
<trans type="CUT" preFNum="46613" postFNum="46614"/>
<trans type="CUT" preFNum="46745" postFNum="46746"/>
<trans type="CUT" preFNum="46894" postFNum="46895"/>
<trans type="CUT" preFNum="47018" postFNum="47019"/>
<trans type="CUT" preFNum="47389" postFNum="47390"/>
<trans type="CUT" preFNum="47681" postFNum="47682"/>
<trans type="CUT" preFNum="48501" postFNum="48502"/>
<trans type="CUT" preFNum="48587" postFNum="48588"/>
<trans type="CUT" preFNum="48723" postFNum="48724"/>
<trans type="CUT" preFNum="48801" postFNum="48802"/>
<trans type="CUT" preFNum="48845" postFNum="48846"/>
<trans type="CUT" preFNum="48941" postFNum="48942"/>
<trans type="CUT" preFNum="48989" postFNum="48990"/>
<trans type="CUT" preFNum="49153" postFNum="49154"/>
<trans type="CUT" preFNum="49267" postFNum="49268"/>
<trans type="CUT" preFNum="49343" postFNum="49344"/>
<trans type="CUT" preFNum="49391" postFNum="49392"/>
<trans type="CUT" preFNum="49429" postFNum="49430"/>
<trans type="CUT" preFNum="49583" postFNum="49584"/>
<trans type="CUT" preFNum="49639" postFNum="49640"/>
<trans type="CUT" preFNum="49687" postFNum="49688"/>
<trans type="CUT" preFNum="49883" postFNum="49884"/>
<trans type="CUT" preFNum="49953" postFNum="49954"/>
<trans type="CUT" preFNum="50101" postFNum="50102"/>
<trans type="CUT" preFNum="50139" postFNum="50140"/>
<trans type="CUT" preFNum="50233" postFNum="50234"/>
<trans type="CUT" preFNum="50361" postFNum="50362"/>
<trans type="CUT" preFNum="50739" postFNum="50740"/>
<trans type="CUT" preFNum="50806" postFNum="50807"/>
<trans type="DIS" preFNum="50964" postFNum="51002"/>
<trans type="FOI" preFNum="51164" postFNum="51223"/>
<trans type="FOI" preFNum="51525" postFNum="51596"/>
<trans type="DIS" preFNum="51735" postFNum="51757"/>
<trans type="DIS" preFNum="51854" postFNum="51871"/>
<trans type="CUT" preFNum="52099" postFNum="52100"/>
<trans type="FOI" preFNum="52196" postFNum="52262"/>
</refSeg>
